michelangelocc/__init__.py
michelangelocc/cli.py
michelangelocc/session.py
michelangelocc/core/__init__.py
michelangelocc/core/exporter.py
michelangelocc/core/modeler.py
michelangelocc/core/repairer.py
michelangelocc/core/validator.py
michelangelocc/server/__init__.py
michelangelocc/server/app.py
michelangelocc/server/watcher.py
michelangelocc/utils/__init__.py
michelangelocc-0.1.0.dist-info/METADATA
michelangelocc-0.1.0.dist-info/WHEEL
michelangelocc-0.1.0.dist-info/entry_points.txt
michelangelocc-0.1.0.dist-info/licenses/LICENSE
michelangelocc-0.1.0.dist-info/RECORD
