Metadata-Version: 2.4
Name: michelangelocc
Version: 0.1.0
Summary: Claude Code-powered 3D model generator for STL files
Project-URL: Homepage, https://github.com/saitotakeuchi/MichelangeloCC
Project-URL: Documentation, https://github.com/saitotakeuchi/MichelangeloCC#readme
Project-URL: Repository, https://github.com/saitotakeuchi/MichelangeloCC.git
Project-URL: Issues, https://github.com/saitotakeuchi/MichelangeloCC/issues
Author: MichelangeloCC Contributors
License-Expression: MIT
License-File: LICENSE
Keywords: 3d-printing,ai,build123d,cad,claude,stl
Classifier: Development Status :: 3 - Alpha
Classifier: Intended Audience :: Developers
Classifier: License :: OSI Approved :: MIT License
Classifier: Programming Language :: Python :: 3.10
Classifier: Programming Language :: Python :: 3.11
Classifier: Programming Language :: Python :: 3.12
Classifier: Topic :: Multimedia :: Graphics :: 3D Modeling
Requires-Python: >=3.10
Requires-Dist: build123d>=0.7.0
Requires-Dist: fastapi>=0.100.0
Requires-Dist: numpy>=1.24.0
Requires-Dist: pydantic>=2.0.0
Requires-Dist: pymeshfix>=0.17.0
Requires-Dist: rich>=13.0.0
Requires-Dist: trimesh>=4.0.0
Requires-Dist: typer[all]>=0.9.0
Requires-Dist: uvicorn[standard]>=0.23.0
Requires-Dist: watchdog>=3.0.0
Requires-Dist: websockets>=11.0
Provides-Extra: dev
Requires-Dist: mypy>=1.0.0; extra == 'dev'
Requires-Dist: pytest-asyncio>=0.21.0; extra == 'dev'
Requires-Dist: pytest-cov>=4.0.0; extra == 'dev'
Requires-Dist: pytest>=7.0.0; extra == 'dev'
Requires-Dist: ruff>=0.1.0; extra == 'dev'
